odoo/addons/account_invoice_report_shipping_ref/README.rst
odoo/addons/account_invoice_report_shipping_ref/__init__.py
odoo/addons/account_invoice_report_shipping_ref/__manifest__.py
odoo/addons/account_invoice_report_shipping_ref/i18n/es.po
odoo/addons/account_invoice_report_shipping_ref/models/__init__.py
odoo/addons/account_invoice_report_shipping_ref/models/res_company.py
odoo/addons/account_invoice_report_shipping_ref/models/res_config_settings.py
odoo/addons/account_invoice_report_shipping_ref/readme/CONFIGURE.md
odoo/addons/account_invoice_report_shipping_ref/readme/CONTRIBUTORS.md
odoo/addons/account_invoice_report_shipping_ref/readme/DESCRIPTION.md
odoo/addons/account_invoice_report_shipping_ref/report/report_invoice.xml
odoo/addons/account_invoice_report_shipping_ref/static/description/icon.png
odoo/addons/account_invoice_report_shipping_ref/static/description/index.html
odoo/addons/account_invoice_report_shipping_ref/views/res_config_settings_views.xml
odoo_addon_account_invoice_report_shipping_ref-17.0.1.0.0.1.dist-info/METADATA
odoo_addon_account_invoice_report_shipping_ref-17.0.1.0.0.1.dist-info/WHEEL
odoo_addon_account_invoice_report_shipping_ref-17.0.1.0.0.1.dist-info/top_level.txt
odoo_addon_account_invoice_report_shipping_ref-17.0.1.0.0.1.dist-info/RECORD
